odoo10_addon_pim-10.0.1.1.0.99.dev4-py3.8-nspkg.pth
odoo/addons/pim/README.rst
odoo/addons/pim/__init__.py
odoo/addons/pim/__manifest__.py
odoo/addons/pim/data/ir_module_category_data.xml
odoo/addons/pim/models/__init__.py
odoo/addons/pim/models/attribute_attribute.py
odoo/addons/pim/models/res_config_settings.py
odoo/addons/pim/readme/CONFIGURE.rst
odoo/addons/pim/readme/CONTRIBUTORS.rst
odoo/addons/pim/readme/DESCRIPTION.rst
odoo/addons/pim/readme/ROADMAP.rst
odoo/addons/pim/readme/USAGE.rst
odoo/addons/pim/security/pim_security.xml
odoo/addons/pim/static/description/icon.png
odoo/addons/pim/static/description/index.html
odoo/addons/pim/tests/__init__.py
odoo/addons/pim/tests/test_pim_attribute_set_mass_edit.py
odoo/addons/pim/views/attribute_attribute.xml
odoo/addons/pim/views/attribute_group.xml
odoo/addons/pim/views/attribute_set.xml
odoo/addons/pim/views/pim_view.xml
odoo/addons/pim/views/product_view.xml
odoo/addons/pim/views/res_config_settings.xml
odoo10_addon_pim-10.0.1.1.0.99.dev4.dist-info/METADATA
odoo10_addon_pim-10.0.1.1.0.99.dev4.dist-info/WHEEL
odoo10_addon_pim-10.0.1.1.0.99.dev4.dist-info/namespace_packages.txt
odoo10_addon_pim-10.0.1.1.0.99.dev4.dist-info/top_level.txt
odoo10_addon_pim-10.0.1.1.0.99.dev4.dist-info/RECORD
