Metadata-Version: 2.1
Name: odoo10-addon-pim
Version: 10.0.1.1.0.99.dev4
Summary: Product Information Management
Home-page: https://github.com/shopinvader/odoo-pim
Author: Akretion
License: AGPL-3
Platform: UNKNOWN
Classifier: Programming Language :: Python
Classifier: Framework :: Odoo
Classifier: Framework :: Odoo :: 10.0
Classifier: License :: OSI Approved :: GNU Affero General Public License v3
Requires-Python: ~=2.7
Requires-Dist: odoo10-addon-attribute-set-mass-edit
Requires-Dist: odoo10-addon-attribute-set-searchable
Requires-Dist: odoo10-addon-product-attribute-set
Requires-Dist: odoo10-addon-product-attribute-set-completeness
Requires-Dist: odoo10-addon-product-search-multi-value
Requires-Dist: odoo <10.1dev,>=10.0
